mkdocs_pluglet_file_include
