Metadata-Version: 2.1
Name: mkdocs-pluglet-file-include
Version: 0.1.1
Summary: include file contents using anchors
Home-page: https://github.com/sebinjohn/mkdocs-pluglet-file-include
Author: Sebin John
Author-email: sebin.john.sebin@gmail.com
License: GPL3
Platform: UNKNOWN
License-File: LICENSE
